<?xml version="1.0" encoding="UTF-8" standalone="no"?>
<persistence xmlns="http://java.sun.com/xml/ns/persistence"
             version="2.0">
    <persistence-unit name="analysis"
                      transaction-type="RESOURCE_LOCAL">
        <class>com.company.mildred.entity.Action</class>
        <class>com.company.mildred.entity.ActionDispatch</class>
        <class>com.company.mildred.entity.ActionParam</class>
        <class>com.company.mildred.entity.ActionStatus</class>
        <class>com.company.mildred.entity.EsSearchFieldSpec</class>
        <class>com.company.mildred.entity.EsSearchSpec</class>
        <class>com.company.mildred.entity.MetaAction</class>
        <class>com.company.mildred.entity.MetaActionParam</class>
        <class>com.company.mildred.entity.MetaReason</class>
        <class>com.company.mildred.entity.MetaReasonParam</class>
        <class>com.company.mildred.entity.Reason</class>
        <class>com.company.mildred.entity.ReasonParam</class>
        <class>com.company.mildred.entity.VectorParam</class>
    </persistence-unit>
</persistence>
